climate_ref_celery/__init__.py
climate_ref_celery/app.py
climate_ref_celery/cli.py
climate_ref_celery/executor.py
climate_ref_celery/py.typed
climate_ref_celery/tasks.py
climate_ref_celery/worker_tasks.py
climate_ref_celery/celeryconf/__init__.py
climate_ref_celery/celeryconf/base.py
climate_ref_celery/celeryconf/dev.py
climate_ref_celery/celeryconf/prod.py
climate_ref_celery-0.8.1.dist-info/METADATA
climate_ref_celery-0.8.1.dist-info/WHEEL
climate_ref_celery-0.8.1.dist-info/entry_points.txt
climate_ref_celery-0.8.1.dist-info/licenses/LICENCE
climate_ref_celery-0.8.1.dist-info/licenses/NOTICE
climate_ref_celery-0.8.1.dist-info/RECORD
