Metadata-Version: 2.4
Name: climate-ref-celery
Version: 0.8.1
Summary: Celery app for mananging tasks and workers
Author-email: Jared Lewis <jared.lewis@climate-resource.com>
License-Expression: Apache-2.0
License-File: LICENCE
License-File: NOTICE
Classifier: Development Status :: 3 - Alpha
Classifier: Intended Audience :: Developers
Classifier: Intended Audience :: Science/Research
Classifier: License :: OSI Approved :: Apache Software License
Classifier: Operating System :: OS Independent
Classifier: Programming Language :: Python
Classifier: Programming Language :: Python :: 3
Classifier: Programming Language :: Python :: 3.11
Classifier: Programming Language :: Python :: 3.12
Classifier: Programming Language :: Python :: 3.13
Classifier: Topic :: Scientific/Engineering
Requires-Python: >=3.11
Requires-Dist: celery[redis]>=5.4.0
Requires-Dist: climate-ref
Requires-Dist: climate-ref-core
Requires-Dist: environs>=11
Requires-Dist: loguru>=0.7.2
Requires-Dist: tqdm>=4.67.1
Requires-Dist: typer>=0.12.0
